[
    {
        "joke": "I wonder why coffins are padded - is it in case they wake up? Memory foam for a death to <word>",
        "choice_1": "remember",
        "choice_2": "spaghetti",
        "choice_3": "astronaut"
    },
    {
        "joke": "Age is just a <word>, that time did on my face",
        "choice_1": "number",
        "choice_2": "banana",
        "choice_3": "unicorn"
    },
    {
        "joke": "Krillin is a good guy, before doing stuff he checked she was <word>.",
        "choice_1": "18",
        "choice_2": "42",
        "choice_3": "69"
    },
    {
        "joke": "Necrophiliacs are very thorough when it comes to their sex lives, they leave no <word> unturned.",
        "choice_1": "tombstone",
        "choice_2": "body",
        "choice_3": "yoghurt"
    },
    {
        "joke": "I think I found my place in the universe: I’m just a <word> between my employer, and my landlord",
        "choice_1": "wire",
        "choice_2": "stupid",
        "choice_3": "guy"
    },
    {
        "joke": "Why don't scientists trust atoms? Because they make up <word>.",
        "choice_1": "everything",
        "choice_2": "pancakes",
        "choice_3": "dance moves"
    },
    {
        "joke": "I'm reading a book on anti-gravity. It's impossible to <word>.",
        "choice_1": "put down",
        "choice_2": "fry eggs",
        "choice_3": "ride unicorns"
    }
]